{
    "Questions": [{
            "Number": 0,
            "Text": "Hi",
            "Type": 0,
            "Answers": [{
                    "Text": "Hello",
                    "NextQuestionNumber": 1
                }, {
                    "Text": "Umm?",
                    "NextQuestionNumber": 2
                }
            ]
        }, {
            "Number": 1,
            "Text": "Ok!",
            "Type": 1,
            "Answers": []
        }, {
            "Number": 2,
            "Text": "You lose!",
            "Type": 2,
            "Answers": []
        }
    ]
}
